<?xml version="1.0"?>
<image signature="sdi2" form="1" version="0">
	<width>2104</width>
	<height>2736</height>
	<color-model>rgb24</color-model>
	<num-levels>13</num-levels>
	<tile-address-scheme>l-xy</tile-address-scheme>
	<bits-per-pixel>0</bits-per-pixel>
	<mean-squared-error>0</mean-squared-error>
	<levels>
		<level index="0">
			<width>1</width>
			<height>1</height>
			<tile-file-format>jpg</tile-file-format>
			<tile-size>
				<width>255</width>
				<height>255</height>
			</tile-size>
			<tile-overlap>
				<left>0</left>
				<top>0</top>
				<right>1</right>
				<bottom>1</bottom>
			</tile-overlap>
			<offset>
				<width>0</width>
				<height>0</height>
			</offset>
		</level>
		<level index="1">
			<width>2</width>
			<height>2</height>
			<tile-file-format>jpg</tile-file-format>
			<tile-size>
				<width>255</width>
				<height>255</height>
			</tile-size>
			<tile-overlap>
				<left>0</left>
				<top>0</top>
				<right>1</right>
				<bottom>1</bottom>
			</tile-overlap>
			<offset>
				<width>0</width>
				<height>0</height>
			</offset>
		</level>
		<level index="2">
			<width>3</width>
			<height>3</height>
			<tile-file-format>jpg</tile-file-format>
			<tile-size>
				<width>255</width>
				<height>255</height>
			</tile-size>
			<tile-overlap>
				<left>0</left>
				<top>0</top>
				<right>1</right>
				<bottom>1</bottom>
			</tile-overlap>
			<offset>
				<width>0</width>
				<height>0</height>
			</offset>
		</level>
		<level index="3">
			<width>5</width>
			<height>6</height>
			<tile-file-format>jpg</tile-file-format>
			<tile-size>
				<width>255</width>
				<height>255</height>
			</tile-size>
			<tile-overlap>
				<left>0</left>
				<top>0</top>
				<right>1</right>
				<bottom>1</bottom>
			</tile-overlap>
			<offset>
				<width>0</width>
				<height>0</height>
			</offset>
		</level>
		<level index="4">
			<width>9</width>
			<height>11</height>
			<tile-file-format>jpg</tile-file-format>
			<tile-size>
				<width>255</width>
				<height>255</height>
			</tile-size>
			<tile-overlap>
				<left>0</left>
				<top>0</top>
				<right>1</right>
				<bottom>1</bottom>
			</tile-overlap>
			<offset>
				<width>0</width>
				<height>0</height>
			</offset>
		</level>
		<level index="5">
			<width>17</width>
			<height>22</height>
			<tile-file-format>jpg</tile-file-format>
			<tile-size>
				<width>255</width>
				<height>255</height>
			</tile-size>
			<tile-overlap>
				<left>0</left>
				<top>0</top>
				<right>1</right>
				<bottom>1</bottom>
			</tile-overlap>
			<offset>
				<width>0</width>
				<height>0</height>
			</offset>
		</level>
		<level index="6">
			<width>33</width>
			<height>43</height>
			<tile-file-format>jpg</tile-file-format>
			<tile-size>
				<width>255</width>
				<height>255</height>
			</tile-size>
			<tile-overlap>
				<left>0</left>
				<top>0</top>
				<right>1</right>
				<bottom>1</bottom>
			</tile-overlap>
			<offset>
				<width>0</width>
				<height>0</height>
			</offset>
		</level>
		<level index="7">
			<width>66</width>
			<height>86</height>
			<tile-file-format>jpg</tile-file-format>
			<tile-size>
				<width>255</width>
				<height>255</height>
			</tile-size>
			<tile-overlap>
				<left>0</left>
				<top>0</top>
				<right>1</right>
				<bottom>1</bottom>
			</tile-overlap>
			<offset>
				<width>0</width>
				<height>0</height>
			</offset>
		</level>
		<level index="8">
			<width>132</width>
			<height>171</height>
			<tile-file-format>jpg</tile-file-format>
			<tile-size>
				<width>255</width>
				<height>255</height>
			</tile-size>
			<tile-overlap>
				<left>0</left>
				<top>0</top>
				<right>1</right>
				<bottom>1</bottom>
			</tile-overlap>
			<offset>
				<width>0</width>
				<height>0</height>
			</offset>
		</level>
		<level index="9">
			<width>263</width>
			<height>342</height>
			<tile-file-format>jpg</tile-file-format>
			<tile-size>
				<width>255</width>
				<height>255</height>
			</tile-size>
			<tile-overlap>
				<left>0</left>
				<top>0</top>
				<right>1</right>
				<bottom>1</bottom>
			</tile-overlap>
			<offset>
				<width>0</width>
				<height>0</height>
			</offset>
		</level>
		<level index="10">
			<width>526</width>
			<height>684</height>
			<tile-file-format>jpg</tile-file-format>
			<tile-size>
				<width>255</width>
				<height>255</height>
			</tile-size>
			<tile-overlap>
				<left>0</left>
				<top>0</top>
				<right>1</right>
				<bottom>1</bottom>
			</tile-overlap>
			<offset>
				<width>0</width>
				<height>0</height>
			</offset>
		</level>
		<level index="11">
			<width>1052</width>
			<height>1368</height>
			<tile-file-format>jpg</tile-file-format>
			<tile-size>
				<width>255</width>
				<height>255</height>
			</tile-size>
			<tile-overlap>
				<left>0</left>
				<top>0</top>
				<right>1</right>
				<bottom>1</bottom>
			</tile-overlap>
			<offset>
				<width>0</width>
				<height>0</height>
			</offset>
		</level>
		<level index="12">
			<width>2104</width>
			<height>2736</height>
			<tile-file-format>jpg</tile-file-format>
			<tile-size>
				<width>255</width>
				<height>255</height>
			</tile-size>
			<tile-overlap>
				<left>0</left>
				<top>0</top>
				<right>1</right>
				<bottom>1</bottom>
			</tile-overlap>
			<offset>
				<width>0</width>
				<height>0</height>
			</offset>
		</level>
	</levels>
</image>
